sender/__init__.py
sender/aliyun_sender.py
sender/base.py
sender/exceptions.py
sender/factory.py
sender/utils.py
sms_send_cjh-0.5.dist-info/LICENSE
sms_send_cjh-0.5.dist-info/METADATA
sms_send_cjh-0.5.dist-info/WHEEL
sms_send_cjh-0.5.dist-info/top_level.txt
sms_send_cjh-0.5.dist-info/RECORD
