Metadata-Version: 2.1
Name: sms_send_cjh
Version: 0.5
Summary: 发送短信包
Home-page: https://github.com/chongjiahao223/sms_sender.git
Author: CJH
Author-email: 942130598@qq.com
Requires-Python: >=3.12
License-File: LICENSE
Requires-Dist: aliyun-python-sdk-core
Requires-Dist: aliyun-python-sdk-dysmsapi
